sequana_pipelines/lora/__init__.py
sequana_pipelines/lora/config.yaml
sequana_pipelines/lora/dag.png
sequana_pipelines/lora/dag.svg
sequana_pipelines/lora/info.py
sequana_pipelines/lora/lora.rules
sequana_pipelines/lora/main.py
sequana_pipelines/lora/multiqc_config.yaml
sequana_pipelines/lora/requirements.json
sequana_pipelines/lora/rules/assembler.smk
sequana_pipelines/lora/rules/ccs.smk
sequana_pipelines/lora/rules/common.smk
sequana_pipelines/lora/rules/polish.smk
sequana_pipelines/lora/rules/qc.smk
sequana_pipelines/lora/rules/scaffold.smk
sequana_pipelines/lora/schema.yaml
sequana_pipelines/lora/src/__init__.py
sequana_pipelines/lora/src/enums.py
sequana_pipelines/lora/src/exceptions.py
sequana_pipelines/lora/src/report.py
sequana_pipelines/lora/src/templates/__init__.py
sequana_pipelines/lora/src/templates/lora.css
sequana_pipelines/lora/src/templates/lora.html
sequana_pipelines/lora/src/templates/lora.js
sequana_pipelines/lora/src/templates/summary.css
sequana_pipelines/lora/src/templates/summary.html
sequana_pipelines/lora/src/templates/summary.js
sequana_pipelines/lora/src/utils.py
sequana_pipelines/lora/tools.txt
sequana_pipelines/matplotlibrc
sequana_lora-1.0.1.dist-info/LICENSE
sequana_lora-1.0.1.dist-info/METADATA
sequana_lora-1.0.1.dist-info/WHEEL
sequana_lora-1.0.1.dist-info/entry_points.txt
sequana_lora-1.0.1.dist-info/RECORD
