Metadata-Version: 2.3
Name: sequana-lora
Version: 1.0.1
Summary: Run assembler (Canu, Flye, Hifiasm) on a set of long read files
License: BSD-3
Keywords: pacbio,nanopore,snakemake,sequana,assembly
Author: Sequana Team
Author-email: thomas.cokelaer@pasteur.fr
Requires-Python: >=3.9,<4.0
Classifier: Development Status :: 5 - Production/Stable
Classifier: Intended Audience :: Education
Classifier: Intended Audience :: End Users/Desktop
Classifier: Intended Audience :: Developers
Classifier: Intended Audience :: Science/Research
Classifier: License :: OSI Approved :: BSD License
Classifier: Operating System :: POSIX :: Linux
Classifier: Programming Language :: Python :: 3.9
Classifier: Programming Language :: Python :: 3.10
Classifier: Programming Language :: Python :: 3.11
Classifier: Topic :: Software Development :: Libraries :: Python Modules
Classifier: Topic :: Scientific/Engineering :: Bio-Informatics
Classifier: Topic :: Scientific/Engineering :: Information Analysis
Requires-Dist: Jinja2 (>=3.1.2)
Requires-Dist: beautifulsoup4
Requires-Dist: click (>=8.1.7)
Requires-Dist: click-completion (>=0.5.2)
Requires-Dist: pandas (>=2.0.0)
Requires-Dist: sequana-pipetools (>=1.3.0)
